traceroute_win/__init__.py
traceroute_win/traceroute_win.py
traceroute_win-2.3.0.dist-info/LICENCE
traceroute_win-2.3.0.dist-info/METADATA
traceroute_win-2.3.0.dist-info/WHEEL
traceroute_win-2.3.0.dist-info/entry_points.txt
traceroute_win-2.3.0.dist-info/top_level.txt
traceroute_win-2.3.0.dist-info/RECORD
